{
  "id": "b6ee8bfd-3d1e-42cf-9af0-a40dec430acb",
  "prevId": "c7457759-0582-4152-bf6c-00c959bcda55",
  "version": "7",
  "dialect": "postgresql",
  "tables": {
    "public.tenants": {
      "name": "tenants",
      "schema": "",
      "columns": {
        "id": {
          "name": "id",
          "type": "uuid",
          "primaryKey": true,
          "notNull": true,
          "default": "gen_random_uuid()"
        },
        "name": {
          "name": "name",
          "type": "varchar(200)",
          "primaryKey": false,
          "notNull": true
        },
        "slug": {
          "name": "slug",
          "type": "varchar(100)",
          "primaryKey": false,
          "notNull": true
        },
        "email": {
          "name": "email",
          "type": "varchar(200)",
          "primaryKey": false,
          "notNull": true
        },
        "active": {
          "name": "active",
          "type": "boolean",
          "primaryKey": false,
          "notNull": true,
          "default": true
        },
        "geocoding_monthly_limit": {
          "name": "geocoding_monthly_limit",
          "type": "integer",
          "primaryKey": false,
          "notNull": false
        },
        "geocoding_limit_expires_at": {
          "name": "geocoding_limit_expires_at",
          "type": "timestamp",
          "primaryKey": false,
          "notNull": false
        },
        "created_at": {
          "name": "created_at",
          "type": "timestamp",
          "primaryKey": false,
          "notNull": true,
          "default": "now()"
        },
        "updated_at": {
          "name": "updated_at",
          "type": "timestamp",
          "primaryKey": false,
          "notNull": true,
          "default": "now()"
        },
        "deleted_at": {
          "name": "deleted_at",
          "type": "timestamp",
          "primaryKey": false,
          "notNull": false
        }
      },
      "indexes": {},
      "foreignKeys": {},
      "compositePrimaryKeys": {},
      "uniqueConstraints": {
        "tenants_slug_unique": {
          "name": "tenants_slug_unique",
          "nullsNotDistinct": false,
          "columns": [
            "slug"
          ]
        }
      },
      "policies": {},
      "checkConstraints": {},
      "isRLSEnabled": false
    },
    "public.pin_types": {
      "name": "pin_types",
      "schema": "",
      "columns": {
        "id": {
          "name": "id",
          "type": "uuid",
          "primaryKey": true,
          "notNull": true,
          "default": "gen_random_uuid()"
        },
        "tenant_id": {
          "name": "tenant_id",
          "type": "uuid",
          "primaryKey": false,
          "notNull": true
        },
        "name": {
          "name": "name",
          "type": "varchar(100)",
          "primaryKey": false,
          "notNull": true
        },
        "color": {
          "name": "color",
          "type": "varchar(7)",
          "primaryKey": false,
          "notNull": true,
          "default": "'#6366f1'"
        },
        "created_at": {
          "name": "created_at",
          "type": "timestamp",
          "primaryKey": false,
          "notNull": true,
          "default": "now()"
        },
        "updated_at": {
          "name": "updated_at",
          "type": "timestamp",
          "primaryKey": false,
          "notNull": true,
          "default": "now()"
        },
        "deleted_at": {
          "name": "deleted_at",
          "type": "timestamp",
          "primaryKey": false,
          "notNull": false
        }
      },
      "indexes": {
        "pin_types_tenant_idx": {
          "name": "pin_types_tenant_idx",
          "columns": [
            {
              "expression": "tenant_id",
              "isExpression": false,
              "asc": true,
              "nulls": "last"
            }
          ],
          "isUnique": false,
          "concurrently": false,
          "method": "btree",
          "with": {}
        },
        "pin_types_tenant_name_unique": {
          "name": "pin_types_tenant_name_unique",
          "columns": [
            {
              "expression": "tenant_id",
              "isExpression": false,
              "asc": true,
              "nulls": "last"
            },
            {
              "expression": "name",
              "isExpression": false,
              "asc": true,
              "nulls": "last"
            }
          ],
          "isUnique": true,
          "concurrently": false,
          "method": "btree",
          "with": {}
        }
      },
      "foreignKeys": {
        "pin_types_tenant_id_tenants_id_fk": {
          "name": "pin_types_tenant_id_tenants_id_fk",
          "tableFrom": "pin_types",
          "tableTo": "tenants",
          "columnsFrom": [
            "tenant_id"
          ],
          "columnsTo": [
            "id"
          ],
          "onDelete": "no action",
          "onUpdate": "no action"
        }
      },
      "compositePrimaryKeys": {},
      "uniqueConstraints": {},
      "policies": {},
      "checkConstraints": {},
      "isRLSEnabled": false
    },
    "public.users": {
      "name": "users",
      "schema": "",
      "columns": {
        "id": {
          "name": "id",
          "type": "uuid",
          "primaryKey": true,
          "notNull": true,
          "default": "gen_random_uuid()"
        },
        "tenant_id": {
          "name": "tenant_id",
          "type": "uuid",
          "primaryKey": false,
          "notNull": true
        },
        "name": {
          "name": "name",
          "type": "varchar(200)",
          "primaryKey": false,
          "notNull": true
        },
        "email": {
          "name": "email",
          "type": "varchar(200)",
          "primaryKey": false,
          "notNull": true
        },
        "password_hash": {
          "name": "password_hash",
          "type": "varchar(500)",
          "primaryKey": false,
          "notNull": false
        },
        "google_id": {
          "name": "google_id",
          "type": "varchar(200)",
          "primaryKey": false,
          "notNull": false
        },
        "role": {
          "name": "role",
          "type": "varchar(30)",
          "primaryKey": false,
          "notNull": true,
          "default": "'employee'"
        },
        "email_verified": {
          "name": "email_verified",
          "type": "boolean",
          "primaryKey": false,
          "notNull": true,
          "default": false
        },
        "email_verify_token": {
          "name": "email_verify_token",
          "type": "varchar(200)",
          "primaryKey": false,
          "notNull": false
        },
        "email_verify_expires_at": {
          "name": "email_verify_expires_at",
          "type": "timestamp",
          "primaryKey": false,
          "notNull": false
        },
        "reset_password_token": {
          "name": "reset_password_token",
          "type": "varchar(200)",
          "primaryKey": false,
          "notNull": false
        },
        "reset_password_expires_at": {
          "name": "reset_password_expires_at",
          "type": "timestamp",
          "primaryKey": false,
          "notNull": false
        },
        "totp_secret": {
          "name": "totp_secret",
          "type": "varchar(200)",
          "primaryKey": false,
          "notNull": false
        },
        "totp_enabled": {
          "name": "totp_enabled",
          "type": "boolean",
          "primaryKey": false,
          "notNull": true,
          "default": false
        },
        "invited_by": {
          "name": "invited_by",
          "type": "uuid",
          "primaryKey": false,
          "notNull": false
        },
        "created_at": {
          "name": "created_at",
          "type": "timestamp",
          "primaryKey": false,
          "notNull": true,
          "default": "now()"
        },
        "updated_at": {
          "name": "updated_at",
          "type": "timestamp",
          "primaryKey": false,
          "notNull": true,
          "default": "now()"
        },
        "deleted_at": {
          "name": "deleted_at",
          "type": "timestamp",
          "primaryKey": false,
          "notNull": false
        }
      },
      "indexes": {
        "users_tenant_idx": {
          "name": "users_tenant_idx",
          "columns": [
            {
              "expression": "tenant_id",
              "isExpression": false,
              "asc": true,
              "nulls": "last"
            }
          ],
          "isUnique": false,
          "concurrently": false,
          "method": "btree",
          "with": {}
        },
        "users_email_idx": {
          "name": "users_email_idx",
          "columns": [
            {
              "expression": "email",
              "isExpression": false,
              "asc": true,
              "nulls": "last"
            }
          ],
          "isUnique": false,
          "concurrently": false,
          "method": "btree",
          "with": {}
        }
      },
      "foreignKeys": {
        "users_tenant_id_tenants_id_fk": {
          "name": "users_tenant_id_tenants_id_fk",
          "tableFrom": "users",
          "tableTo": "tenants",
          "columnsFrom": [
            "tenant_id"
          ],
          "columnsTo": [
            "id"
          ],
          "onDelete": "no action",
          "onUpdate": "no action"
        },
        "users_invited_by_users_id_fk": {
          "name": "users_invited_by_users_id_fk",
          "tableFrom": "users",
          "tableTo": "users",
          "columnsFrom": [
            "invited_by"
          ],
          "columnsTo": [
            "id"
          ],
          "onDelete": "no action",
          "onUpdate": "no action"
        }
      },
      "compositePrimaryKeys": {},
      "uniqueConstraints": {
        "users_email_unique": {
          "name": "users_email_unique",
          "nullsNotDistinct": false,
          "columns": [
            "email"
          ]
        },
        "users_google_id_unique": {
          "name": "users_google_id_unique",
          "nullsNotDistinct": false,
          "columns": [
            "google_id"
          ]
        }
      },
      "policies": {},
      "checkConstraints": {},
      "isRLSEnabled": false
    },
    "public.subscriptions": {
      "name": "subscriptions",
      "schema": "",
      "columns": {
        "id": {
          "name": "id",
          "type": "uuid",
          "primaryKey": true,
          "notNull": true,
          "default": "gen_random_uuid()"
        },
        "tenant_id": {
          "name": "tenant_id",
          "type": "uuid",
          "primaryKey": false,
          "notNull": true
        },
        "stripe_customer_id": {
          "name": "stripe_customer_id",
          "type": "varchar(200)",
          "primaryKey": false,
          "notNull": false
        },
        "stripe_subscription_id": {
          "name": "stripe_subscription_id",
          "type": "varchar(200)",
          "primaryKey": false,
          "notNull": false
        },
        "status": {
          "name": "status",
          "type": "varchar(30)",
          "primaryKey": false,
          "notNull": true,
          "default": "'trialing'"
        },
        "plan_type": {
          "name": "plan_type",
          "type": "varchar(20)",
          "primaryKey": false,
          "notNull": false
        },
        "trial_ends_at": {
          "name": "trial_ends_at",
          "type": "timestamp",
          "primaryKey": false,
          "notNull": false
        },
        "current_period_start": {
          "name": "current_period_start",
          "type": "timestamp",
          "primaryKey": false,
          "notNull": false
        },
        "current_period_end": {
          "name": "current_period_end",
          "type": "timestamp",
          "primaryKey": false,
          "notNull": false
        },
        "canceled_at": {
          "name": "canceled_at",
          "type": "timestamp",
          "primaryKey": false,
          "notNull": false
        },
        "created_at": {
          "name": "created_at",
          "type": "timestamp",
          "primaryKey": false,
          "notNull": true,
          "default": "now()"
        },
        "updated_at": {
          "name": "updated_at",
          "type": "timestamp",
          "primaryKey": false,
          "notNull": true,
          "default": "now()"
        }
      },
      "indexes": {},
      "foreignKeys": {
        "subscriptions_tenant_id_tenants_id_fk": {
          "name": "subscriptions_tenant_id_tenants_id_fk",
          "tableFrom": "subscriptions",
          "tableTo": "tenants",
          "columnsFrom": [
            "tenant_id"
          ],
          "columnsTo": [
            "id"
          ],
          "onDelete": "no action",
          "onUpdate": "no action"
        }
      },
      "compositePrimaryKeys": {},
      "uniqueConstraints": {
        "subscriptions_tenant_id_unique": {
          "name": "subscriptions_tenant_id_unique",
          "nullsNotDistinct": false,
          "columns": [
            "tenant_id"
          ]
        }
      },
      "policies": {},
      "checkConstraints": {},
      "isRLSEnabled": false
    },
    "public.refresh_tokens": {
      "name": "refresh_tokens",
      "schema": "",
      "columns": {
        "id": {
          "name": "id",
          "type": "uuid",
          "primaryKey": true,
          "notNull": true,
          "default": "gen_random_uuid()"
        },
        "user_id": {
          "name": "user_id",
          "type": "uuid",
          "primaryKey": false,
          "notNull": true
        },
        "tenant_id": {
          "name": "tenant_id",
          "type": "uuid",
          "primaryKey": false,
          "notNull": true
        },
        "token": {
          "name": "token",
          "type": "varchar(500)",
          "primaryKey": false,
          "notNull": true
        },
        "family_id": {
          "name": "family_id",
          "type": "uuid",
          "primaryKey": false,
          "notNull": true,
          "default": "gen_random_uuid()"
        },
        "expires_at": {
          "name": "expires_at",
          "type": "timestamp",
          "primaryKey": false,
          "notNull": true
        },
        "revoked_at": {
          "name": "revoked_at",
          "type": "timestamp",
          "primaryKey": false,
          "notNull": false
        },
        "created_at": {
          "name": "created_at",
          "type": "timestamp",
          "primaryKey": false,
          "notNull": true,
          "default": "now()"
        }
      },
      "indexes": {
        "refresh_tokens_token_idx": {
          "name": "refresh_tokens_token_idx",
          "columns": [
            {
              "expression": "token",
              "isExpression": false,
              "asc": true,
              "nulls": "last"
            }
          ],
          "isUnique": false,
          "concurrently": false,
          "method": "btree",
          "with": {}
        },
        "refresh_tokens_user_idx": {
          "name": "refresh_tokens_user_idx",
          "columns": [
            {
              "expression": "user_id",
              "isExpression": false,
              "asc": true,
              "nulls": "last"
            }
          ],
          "isUnique": false,
          "concurrently": false,
          "method": "btree",
          "with": {}
        },
        "refresh_tokens_family_idx": {
          "name": "refresh_tokens_family_idx",
          "columns": [
            {
              "expression": "family_id",
              "isExpression": false,
              "asc": true,
              "nulls": "last"
            }
          ],
          "isUnique": false,
          "concurrently": false,
          "method": "btree",
          "with": {}
        }
      },
      "foreignKeys": {
        "refresh_tokens_user_id_users_id_fk": {
          "name": "refresh_tokens_user_id_users_id_fk",
          "tableFrom": "refresh_tokens",
          "tableTo": "users",
          "columnsFrom": [
            "user_id"
          ],
          "columnsTo": [
            "id"
          ],
          "onDelete": "cascade",
          "onUpdate": "no action"
        },
        "refresh_tokens_tenant_id_tenants_id_fk": {
          "name": "refresh_tokens_tenant_id_tenants_id_fk",
          "tableFrom": "refresh_tokens",
          "tableTo": "tenants",
          "columnsFrom": [
            "tenant_id"
          ],
          "columnsTo": [
            "id"
          ],
          "onDelete": "no action",
          "onUpdate": "no action"
        }
      },
      "compositePrimaryKeys": {},
      "uniqueConstraints": {
        "refresh_tokens_token_unique": {
          "name": "refresh_tokens_token_unique",
          "nullsNotDistinct": false,
          "columns": [
            "token"
          ]
        }
      },
      "policies": {},
      "checkConstraints": {},
      "isRLSEnabled": false
    },
    "public.partners": {
      "name": "partners",
      "schema": "",
      "columns": {
        "id": {
          "name": "id",
          "type": "uuid",
          "primaryKey": true,
          "notNull": true,
          "default": "gen_random_uuid()"
        },
        "tenant_id": {
          "name": "tenant_id",
          "type": "uuid",
          "primaryKey": false,
          "notNull": true
        },
        "name": {
          "name": "name",
          "type": "varchar(200)",
          "primaryKey": false,
          "notNull": true
        },
        "address": {
          "name": "address",
          "type": "text",
          "primaryKey": false,
          "notNull": true
        },
        "lat": {
          "name": "lat",
          "type": "double precision",
          "primaryKey": false,
          "notNull": false
        },
        "lng": {
          "name": "lng",
          "type": "double precision",
          "primaryKey": false,
          "notNull": false
        },
        "geocoded_at": {
          "name": "geocoded_at",
          "type": "timestamp",
          "primaryKey": false,
          "notNull": false
        },
        "geocode_status": {
          "name": "geocode_status",
          "type": "varchar(20)",
          "primaryKey": false,
          "notNull": false,
          "default": "'pending'"
        },
        "pin_type_id": {
          "name": "pin_type_id",
          "type": "uuid",
          "primaryKey": false,
          "notNull": false
        },
        "visibility": {
          "name": "visibility",
          "type": "varchar(20)",
          "primaryKey": false,
          "notNull": true,
          "default": "'public'"
        },
        "source": {
          "name": "source",
          "type": "varchar(20)",
          "primaryKey": false,
          "notNull": false,
          "default": "'dashboard'"
        },
        "external_key": {
          "name": "external_key",
          "type": "varchar(300)",
          "primaryKey": false,
          "notNull": false
        },
        "city": {
          "name": "city",
          "type": "varchar(200)",
          "primaryKey": false,
          "notNull": false
        },
        "state": {
          "name": "state",
          "type": "varchar(100)",
          "primaryKey": false,
          "notNull": false
        },
        "notes": {
          "name": "notes",
          "type": "text",
          "primaryKey": false,
          "notNull": false
        },
        "import_job_id": {
          "name": "import_job_id",
          "type": "uuid",
          "primaryKey": false,
          "notNull": false
        },
        "deleted_by_job_id": {
          "name": "deleted_by_job_id",
          "type": "uuid",
          "primaryKey": false,
          "notNull": false
        },
        "created_at": {
          "name": "created_at",
          "type": "timestamp",
          "primaryKey": false,
          "notNull": true,
          "default": "now()"
        },
        "updated_at": {
          "name": "updated_at",
          "type": "timestamp",
          "primaryKey": false,
          "notNull": true,
          "default": "now()"
        },
        "deleted_at": {
          "name": "deleted_at",
          "type": "timestamp",
          "primaryKey": false,
          "notNull": false
        }
      },
      "indexes": {
        "partners_tenant_idx": {
          "name": "partners_tenant_idx",
          "columns": [
            {
              "expression": "tenant_id",
              "isExpression": false,
              "asc": true,
              "nulls": "last"
            }
          ],
          "isUnique": false,
          "concurrently": false,
          "method": "btree",
          "with": {}
        },
        "partners_extkey_idx": {
          "name": "partners_extkey_idx",
          "columns": [
            {
              "expression": "tenant_id",
              "isExpression": false,
              "asc": true,
              "nulls": "last"
            },
            {
              "expression": "external_key",
              "isExpression": false,
              "asc": true,
              "nulls": "last"
            }
          ],
          "isUnique": false,
          "concurrently": false,
          "method": "btree",
          "with": {}
        },
        "partners_latlng_idx": {
          "name": "partners_latlng_idx",
          "columns": [
            {
              "expression": "lat",
              "isExpression": false,
              "asc": true,
              "nulls": "last"
            },
            {
              "expression": "lng",
              "isExpression": false,
              "asc": true,
              "nulls": "last"
            }
          ],
          "isUnique": false,
          "concurrently": false,
          "method": "btree",
          "with": {}
        },
        "partners_visibility_idx": {
          "name": "partners_visibility_idx",
          "columns": [
            {
              "expression": "tenant_id",
              "isExpression": false,
              "asc": true,
              "nulls": "last"
            },
            {
              "expression": "visibility",
              "isExpression": false,
              "asc": true,
              "nulls": "last"
            }
          ],
          "isUnique": false,
          "concurrently": false,
          "method": "btree",
          "with": {}
        },
        "partners_pin_type_idx": {
          "name": "partners_pin_type_idx",
          "columns": [
            {
              "expression": "pin_type_id",
              "isExpression": false,
              "asc": true,
              "nulls": "last"
            }
          ],
          "isUnique": false,
          "concurrently": false,
          "method": "btree",
          "with": {}
        }
      },
      "foreignKeys": {
        "partners_tenant_id_tenants_id_fk": {
          "name": "partners_tenant_id_tenants_id_fk",
          "tableFrom": "partners",
          "tableTo": "tenants",
          "columnsFrom": [
            "tenant_id"
          ],
          "columnsTo": [
            "id"
          ],
          "onDelete": "no action",
          "onUpdate": "no action"
        },
        "partners_pin_type_id_pin_types_id_fk": {
          "name": "partners_pin_type_id_pin_types_id_fk",
          "tableFrom": "partners",
          "tableTo": "pin_types",
          "columnsFrom": [
            "pin_type_id"
          ],
          "columnsTo": [
            "id"
          ],
          "onDelete": "no action",
          "onUpdate": "no action"
        }
      },
      "compositePrimaryKeys": {},
      "uniqueConstraints": {},
      "policies": {},
      "checkConstraints": {},
      "isRLSEnabled": false
    },
    "public.partner_columns": {
      "name": "partner_columns",
      "schema": "",
      "columns": {
        "id": {
          "name": "id",
          "type": "uuid",
          "primaryKey": true,
          "notNull": true,
          "default": "gen_random_uuid()"
        },
        "tenant_id": {
          "name": "tenant_id",
          "type": "uuid",
          "primaryKey": false,
          "notNull": true
        },
        "key": {
          "name": "key",
          "type": "varchar(100)",
          "primaryKey": false,
          "notNull": true
        },
        "label": {
          "name": "label",
          "type": "varchar(200)",
          "primaryKey": false,
          "notNull": true
        },
        "data_type": {
          "name": "data_type",
          "type": "varchar(20)",
          "primaryKey": false,
          "notNull": false,
          "default": "'text'"
        },
        "visible": {
          "name": "visible",
          "type": "boolean",
          "primaryKey": false,
          "notNull": false,
          "default": true
        },
        "sort_order": {
          "name": "sort_order",
          "type": "integer",
          "primaryKey": false,
          "notNull": false,
          "default": 0
        },
        "created_at": {
          "name": "created_at",
          "type": "timestamp",
          "primaryKey": false,
          "notNull": true,
          "default": "now()"
        },
        "updated_at": {
          "name": "updated_at",
          "type": "timestamp",
          "primaryKey": false,
          "notNull": true,
          "default": "now()"
        }
      },
      "indexes": {
        "partner_columns_tenant_key_unique": {
          "name": "partner_columns_tenant_key_unique",
          "columns": [
            {
              "expression": "tenant_id",
              "isExpression": false,
              "asc": true,
              "nulls": "last"
            },
            {
              "expression": "key",
              "isExpression": false,
              "asc": true,
              "nulls": "last"
            }
          ],
          "isUnique": true,
          "concurrently": false,
          "method": "btree",
          "with": {}
        }
      },
      "foreignKeys": {
        "partner_columns_tenant_id_tenants_id_fk": {
          "name": "partner_columns_tenant_id_tenants_id_fk",
          "tableFrom": "partner_columns",
          "tableTo": "tenants",
          "columnsFrom": [
            "tenant_id"
          ],
          "columnsTo": [
            "id"
          ],
          "onDelete": "no action",
          "onUpdate": "no action"
        }
      },
      "compositePrimaryKeys": {},
      "uniqueConstraints": {},
      "policies": {},
      "checkConstraints": {},
      "isRLSEnabled": false
    },
    "public.partner_values": {
      "name": "partner_values",
      "schema": "",
      "columns": {
        "id": {
          "name": "id",
          "type": "uuid",
          "primaryKey": true,
          "notNull": true,
          "default": "gen_random_uuid()"
        },
        "partner_id": {
          "name": "partner_id",
          "type": "uuid",
          "primaryKey": false,
          "notNull": true
        },
        "column_id": {
          "name": "column_id",
          "type": "uuid",
          "primaryKey": false,
          "notNull": true
        },
        "value": {
          "name": "value",
          "type": "text",
          "primaryKey": false,
          "notNull": false
        }
      },
      "indexes": {
        "partner_values_partner_column_unique": {
          "name": "partner_values_partner_column_unique",
          "columns": [
            {
              "expression": "partner_id",
              "isExpression": false,
              "asc": true,
              "nulls": "last"
            },
            {
              "expression": "column_id",
              "isExpression": false,
              "asc": true,
              "nulls": "last"
            }
          ],
          "isUnique": true,
          "concurrently": false,
          "method": "btree",
          "with": {}
        },
        "partner_values_partner_idx": {
          "name": "partner_values_partner_idx",
          "columns": [
            {
              "expression": "partner_id",
              "isExpression": false,
              "asc": true,
              "nulls": "last"
            }
          ],
          "isUnique": false,
          "concurrently": false,
          "method": "btree",
          "with": {}
        }
      },
      "foreignKeys": {
        "partner_values_partner_id_partners_id_fk": {
          "name": "partner_values_partner_id_partners_id_fk",
          "tableFrom": "partner_values",
          "tableTo": "partners",
          "columnsFrom": [
            "partner_id"
          ],
          "columnsTo": [
            "id"
          ],
          "onDelete": "cascade",
          "onUpdate": "no action"
        },
        "partner_values_column_id_partner_columns_id_fk": {
          "name": "partner_values_column_id_partner_columns_id_fk",
          "tableFrom": "partner_values",
          "tableTo": "partner_columns",
          "columnsFrom": [
            "column_id"
          ],
          "columnsTo": [
            "id"
          ],
          "onDelete": "no action",
          "onUpdate": "no action"
        }
      },
      "compositePrimaryKeys": {},
      "uniqueConstraints": {},
      "policies": {},
      "checkConstraints": {},
      "isRLSEnabled": false
    },
    "public.import_jobs": {
      "name": "import_jobs",
      "schema": "",
      "columns": {
        "id": {
          "name": "id",
          "type": "uuid",
          "primaryKey": true,
          "notNull": true,
          "default": "gen_random_uuid()"
        },
        "tenant_id": {
          "name": "tenant_id",
          "type": "uuid",
          "primaryKey": false,
          "notNull": true
        },
        "user_id": {
          "name": "user_id",
          "type": "uuid",
          "primaryKey": false,
          "notNull": true
        },
        "status": {
          "name": "status",
          "type": "varchar(20)",
          "primaryKey": false,
          "notNull": true,
          "default": "'queued'"
        },
        "mode": {
          "name": "mode",
          "type": "varchar(20)",
          "primaryKey": false,
          "notNull": true,
          "default": "'full'"
        },
        "file_name": {
          "name": "file_name",
          "type": "varchar(300)",
          "primaryKey": false,
          "notNull": false
        },
        "file_size": {
          "name": "file_size",
          "type": "integer",
          "primaryKey": false,
          "notNull": false
        },
        "total_rows": {
          "name": "total_rows",
          "type": "integer",
          "primaryKey": false,
          "notNull": false
        },
        "processed_rows": {
          "name": "processed_rows",
          "type": "integer",
          "primaryKey": false,
          "notNull": false,
          "default": 0
        },
        "created": {
          "name": "created",
          "type": "integer",
          "primaryKey": false,
          "notNull": false,
          "default": 0
        },
        "updated": {
          "name": "updated",
          "type": "integer",
          "primaryKey": false,
          "notNull": false,
          "default": 0
        },
        "removed": {
          "name": "removed",
          "type": "integer",
          "primaryKey": false,
          "notNull": false,
          "default": 0
        },
        "failed": {
          "name": "failed",
          "type": "integer",
          "primaryKey": false,
          "notNull": false,
          "default": 0
        },
        "error_log": {
          "name": "error_log",
          "type": "jsonb",
          "primaryKey": false,
          "notNull": false
        },
        "started_at": {
          "name": "started_at",
          "type": "timestamp",
          "primaryKey": false,
          "notNull": false
        },
        "finished_at": {
          "name": "finished_at",
          "type": "timestamp",
          "primaryKey": false,
          "notNull": false
        },
        "rolled_back_at": {
          "name": "rolled_back_at",
          "type": "timestamp",
          "primaryKey": false,
          "notNull": false
        },
        "created_at": {
          "name": "created_at",
          "type": "timestamp",
          "primaryKey": false,
          "notNull": true,
          "default": "now()"
        }
      },
      "indexes": {},
      "foreignKeys": {
        "import_jobs_tenant_id_tenants_id_fk": {
          "name": "import_jobs_tenant_id_tenants_id_fk",
          "tableFrom": "import_jobs",
          "tableTo": "tenants",
          "columnsFrom": [
            "tenant_id"
          ],
          "columnsTo": [
            "id"
          ],
          "onDelete": "no action",
          "onUpdate": "no action"
        },
        "import_jobs_user_id_users_id_fk": {
          "name": "import_jobs_user_id_users_id_fk",
          "tableFrom": "import_jobs",
          "tableTo": "users",
          "columnsFrom": [
            "user_id"
          ],
          "columnsTo": [
            "id"
          ],
          "onDelete": "no action",
          "onUpdate": "no action"
        }
      },
      "compositePrimaryKeys": {},
      "uniqueConstraints": {},
      "policies": {},
      "checkConstraints": {},
      "isRLSEnabled": false
    },
    "public.maps": {
      "name": "maps",
      "schema": "",
      "columns": {
        "id": {
          "name": "id",
          "type": "uuid",
          "primaryKey": true,
          "notNull": true,
          "default": "gen_random_uuid()"
        },
        "tenant_id": {
          "name": "tenant_id",
          "type": "uuid",
          "primaryKey": false,
          "notNull": true
        },
        "name": {
          "name": "name",
          "type": "varchar(120)",
          "primaryKey": false,
          "notNull": true
        },
        "type": {
          "name": "type",
          "type": "varchar(20)",
          "primaryKey": false,
          "notNull": true
        },
        "embed_token": {
          "name": "embed_token",
          "type": "varchar(100)",
          "primaryKey": false,
          "notNull": false
        },
        "filters": {
          "name": "filters",
          "type": "jsonb",
          "primaryKey": false,
          "notNull": false
        },
        "active": {
          "name": "active",
          "type": "boolean",
          "primaryKey": false,
          "notNull": true,
          "default": true
        },
        "created_at": {
          "name": "created_at",
          "type": "timestamp",
          "primaryKey": false,
          "notNull": true,
          "default": "now()"
        },
        "deleted_at": {
          "name": "deleted_at",
          "type": "timestamp",
          "primaryKey": false,
          "notNull": false
        }
      },
      "indexes": {},
      "foreignKeys": {
        "maps_tenant_id_tenants_id_fk": {
          "name": "maps_tenant_id_tenants_id_fk",
          "tableFrom": "maps",
          "tableTo": "tenants",
          "columnsFrom": [
            "tenant_id"
          ],
          "columnsTo": [
            "id"
          ],
          "onDelete": "no action",
          "onUpdate": "no action"
        }
      },
      "compositePrimaryKeys": {},
      "uniqueConstraints": {
        "maps_embed_token_unique": {
          "name": "maps_embed_token_unique",
          "nullsNotDistinct": false,
          "columns": [
            "embed_token"
          ]
        }
      },
      "policies": {},
      "checkConstraints": {},
      "isRLSEnabled": false
    },
    "public.tenant_settings": {
      "name": "tenant_settings",
      "schema": "",
      "columns": {
        "id": {
          "name": "id",
          "type": "uuid",
          "primaryKey": true,
          "notNull": true,
          "default": "gen_random_uuid()"
        },
        "tenant_id": {
          "name": "tenant_id",
          "type": "uuid",
          "primaryKey": false,
          "notNull": true
        },
        "default_map_zoom": {
          "name": "default_map_zoom",
          "type": "integer",
          "primaryKey": false,
          "notNull": false,
          "default": 12
        },
        "default_map_lat": {
          "name": "default_map_lat",
          "type": "double precision",
          "primaryKey": false,
          "notNull": false
        },
        "default_map_lng": {
          "name": "default_map_lng",
          "type": "double precision",
          "primaryKey": false,
          "notNull": false
        },
        "public_map_enabled": {
          "name": "public_map_enabled",
          "type": "boolean",
          "primaryKey": false,
          "notNull": false,
          "default": true
        },
        "public_map_token": {
          "name": "public_map_token",
          "type": "varchar(100)",
          "primaryKey": false,
          "notNull": false
        },
        "brand_logo_url": {
          "name": "brand_logo_url",
          "type": "varchar(500)",
          "primaryKey": false,
          "notNull": false
        },
        "brand_name": {
          "name": "brand_name",
          "type": "varchar(200)",
          "primaryKey": false,
          "notNull": false
        },
        "brand_website_url": {
          "name": "brand_website_url",
          "type": "varchar(500)",
          "primaryKey": false,
          "notNull": false
        },
        "brand_color": {
          "name": "brand_color",
          "type": "varchar(7)",
          "primaryKey": false,
          "notNull": false
        },
        "brand_footer_text": {
          "name": "brand_footer_text",
          "type": "varchar(300)",
          "primaryKey": false,
          "notNull": false
        },
        "updated_at": {
          "name": "updated_at",
          "type": "timestamp",
          "primaryKey": false,
          "notNull": true,
          "default": "now()"
        }
      },
      "indexes": {},
      "foreignKeys": {
        "tenant_settings_tenant_id_tenants_id_fk": {
          "name": "tenant_settings_tenant_id_tenants_id_fk",
          "tableFrom": "tenant_settings",
          "tableTo": "tenants",
          "columnsFrom": [
            "tenant_id"
          ],
          "columnsTo": [
            "id"
          ],
          "onDelete": "no action",
          "onUpdate": "no action"
        }
      },
      "compositePrimaryKeys": {},
      "uniqueConstraints": {
        "tenant_settings_tenant_id_unique": {
          "name": "tenant_settings_tenant_id_unique",
          "nullsNotDistinct": false,
          "columns": [
            "tenant_id"
          ]
        }
      },
      "policies": {},
      "checkConstraints": {},
      "isRLSEnabled": false
    },
    "public.totp_recovery_codes": {
      "name": "totp_recovery_codes",
      "schema": "",
      "columns": {
        "id": {
          "name": "id",
          "type": "uuid",
          "primaryKey": true,
          "notNull": true,
          "default": "gen_random_uuid()"
        },
        "user_id": {
          "name": "user_id",
          "type": "uuid",
          "primaryKey": false,
          "notNull": true
        },
        "code_hash": {
          "name": "code_hash",
          "type": "varchar(300)",
          "primaryKey": false,
          "notNull": true
        },
        "used_at": {
          "name": "used_at",
          "type": "timestamp",
          "primaryKey": false,
          "notNull": false
        },
        "created_at": {
          "name": "created_at",
          "type": "timestamp",
          "primaryKey": false,
          "notNull": true,
          "default": "now()"
        }
      },
      "indexes": {},
      "foreignKeys": {
        "totp_recovery_codes_user_id_users_id_fk": {
          "name": "totp_recovery_codes_user_id_users_id_fk",
          "tableFrom": "totp_recovery_codes",
          "tableTo": "users",
          "columnsFrom": [
            "user_id"
          ],
          "columnsTo": [
            "id"
          ],
          "onDelete": "cascade",
          "onUpdate": "no action"
        }
      },
      "compositePrimaryKeys": {},
      "uniqueConstraints": {},
      "policies": {},
      "checkConstraints": {},
      "isRLSEnabled": false
    },
    "public.tickets": {
      "name": "tickets",
      "schema": "",
      "columns": {
        "id": {
          "name": "id",
          "type": "uuid",
          "primaryKey": true,
          "notNull": true,
          "default": "gen_random_uuid()"
        },
        "tenant_id": {
          "name": "tenant_id",
          "type": "uuid",
          "primaryKey": false,
          "notNull": true
        },
        "user_id": {
          "name": "user_id",
          "type": "uuid",
          "primaryKey": false,
          "notNull": true
        },
        "title": {
          "name": "title",
          "type": "varchar(300)",
          "primaryKey": false,
          "notNull": true
        },
        "body": {
          "name": "body",
          "type": "text",
          "primaryKey": false,
          "notNull": true
        },
        "status": {
          "name": "status",
          "type": "varchar(20)",
          "primaryKey": false,
          "notNull": true,
          "default": "'open'"
        },
        "created_at": {
          "name": "created_at",
          "type": "timestamp",
          "primaryKey": false,
          "notNull": true,
          "default": "now()"
        },
        "updated_at": {
          "name": "updated_at",
          "type": "timestamp",
          "primaryKey": false,
          "notNull": true,
          "default": "now()"
        }
      },
      "indexes": {},
      "foreignKeys": {
        "tickets_tenant_id_tenants_id_fk": {
          "name": "tickets_tenant_id_tenants_id_fk",
          "tableFrom": "tickets",
          "tableTo": "tenants",
          "columnsFrom": [
            "tenant_id"
          ],
          "columnsTo": [
            "id"
          ],
          "onDelete": "no action",
          "onUpdate": "no action"
        },
        "tickets_user_id_users_id_fk": {
          "name": "tickets_user_id_users_id_fk",
          "tableFrom": "tickets",
          "tableTo": "users",
          "columnsFrom": [
            "user_id"
          ],
          "columnsTo": [
            "id"
          ],
          "onDelete": "no action",
          "onUpdate": "no action"
        }
      },
      "compositePrimaryKeys": {},
      "uniqueConstraints": {},
      "policies": {},
      "checkConstraints": {},
      "isRLSEnabled": false
    },
    "public.ticket_messages": {
      "name": "ticket_messages",
      "schema": "",
      "columns": {
        "id": {
          "name": "id",
          "type": "uuid",
          "primaryKey": true,
          "notNull": true,
          "default": "gen_random_uuid()"
        },
        "ticket_id": {
          "name": "ticket_id",
          "type": "uuid",
          "primaryKey": false,
          "notNull": true
        },
        "user_id": {
          "name": "user_id",
          "type": "uuid",
          "primaryKey": false,
          "notNull": true
        },
        "body": {
          "name": "body",
          "type": "text",
          "primaryKey": false,
          "notNull": true
        },
        "is_staff": {
          "name": "is_staff",
          "type": "boolean",
          "primaryKey": false,
          "notNull": true,
          "default": false
        },
        "created_at": {
          "name": "created_at",
          "type": "timestamp",
          "primaryKey": false,
          "notNull": true,
          "default": "now()"
        }
      },
      "indexes": {},
      "foreignKeys": {
        "ticket_messages_ticket_id_tickets_id_fk": {
          "name": "ticket_messages_ticket_id_tickets_id_fk",
          "tableFrom": "ticket_messages",
          "tableTo": "tickets",
          "columnsFrom": [
            "ticket_id"
          ],
          "columnsTo": [
            "id"
          ],
          "onDelete": "cascade",
          "onUpdate": "no action"
        },
        "ticket_messages_user_id_users_id_fk": {
          "name": "ticket_messages_user_id_users_id_fk",
          "tableFrom": "ticket_messages",
          "tableTo": "users",
          "columnsFrom": [
            "user_id"
          ],
          "columnsTo": [
            "id"
          ],
          "onDelete": "no action",
          "onUpdate": "no action"
        }
      },
      "compositePrimaryKeys": {},
      "uniqueConstraints": {},
      "policies": {},
      "checkConstraints": {},
      "isRLSEnabled": false
    },
    "public.geocoding_logs": {
      "name": "geocoding_logs",
      "schema": "",
      "columns": {
        "id": {
          "name": "id",
          "type": "uuid",
          "primaryKey": true,
          "notNull": true,
          "default": "gen_random_uuid()"
        },
        "partner_id": {
          "name": "partner_id",
          "type": "uuid",
          "primaryKey": false,
          "notNull": true
        },
        "tenant_id": {
          "name": "tenant_id",
          "type": "uuid",
          "primaryKey": false,
          "notNull": true
        },
        "address": {
          "name": "address",
          "type": "text",
          "primaryKey": false,
          "notNull": true
        },
        "status": {
          "name": "status",
          "type": "varchar(20)",
          "primaryKey": false,
          "notNull": true
        },
        "error_reason": {
          "name": "error_reason",
          "type": "text",
          "primaryKey": false,
          "notNull": false
        },
        "provider": {
          "name": "provider",
          "type": "varchar(50)",
          "primaryKey": false,
          "notNull": true,
          "default": "'nominatim'"
        },
        "lat": {
          "name": "lat",
          "type": "double precision",
          "primaryKey": false,
          "notNull": false
        },
        "lng": {
          "name": "lng",
          "type": "double precision",
          "primaryKey": false,
          "notNull": false
        },
        "attempted_at": {
          "name": "attempted_at",
          "type": "timestamp",
          "primaryKey": false,
          "notNull": true,
          "default": "now()"
        }
      },
      "indexes": {},
      "foreignKeys": {
        "geocoding_logs_partner_id_partners_id_fk": {
          "name": "geocoding_logs_partner_id_partners_id_fk",
          "tableFrom": "geocoding_logs",
          "tableTo": "partners",
          "columnsFrom": [
            "partner_id"
          ],
          "columnsTo": [
            "id"
          ],
          "onDelete": "cascade",
          "onUpdate": "no action"
        },
        "geocoding_logs_tenant_id_tenants_id_fk": {
          "name": "geocoding_logs_tenant_id_tenants_id_fk",
          "tableFrom": "geocoding_logs",
          "tableTo": "tenants",
          "columnsFrom": [
            "tenant_id"
          ],
          "columnsTo": [
            "id"
          ],
          "onDelete": "no action",
          "onUpdate": "no action"
        }
      },
      "compositePrimaryKeys": {},
      "uniqueConstraints": {},
      "policies": {},
      "checkConstraints": {},
      "isRLSEnabled": false
    },
    "public.geocoding_credit_packs": {
      "name": "geocoding_credit_packs",
      "schema": "",
      "columns": {
        "id": {
          "name": "id",
          "type": "uuid",
          "primaryKey": true,
          "notNull": true,
          "default": "gen_random_uuid()"
        },
        "tenant_id": {
          "name": "tenant_id",
          "type": "uuid",
          "primaryKey": false,
          "notNull": true
        },
        "quantity": {
          "name": "quantity",
          "type": "integer",
          "primaryKey": false,
          "notNull": true
        },
        "remaining": {
          "name": "remaining",
          "type": "integer",
          "primaryKey": false,
          "notNull": true
        },
        "expires_at": {
          "name": "expires_at",
          "type": "timestamp",
          "primaryKey": false,
          "notNull": true
        },
        "stripe_session_id": {
          "name": "stripe_session_id",
          "type": "varchar(200)",
          "primaryKey": false,
          "notNull": false
        },
        "amount_cents": {
          "name": "amount_cents",
          "type": "integer",
          "primaryKey": false,
          "notNull": false
        },
        "created_at": {
          "name": "created_at",
          "type": "timestamp",
          "primaryKey": false,
          "notNull": true,
          "default": "now()"
        }
      },
      "indexes": {},
      "foreignKeys": {
        "geocoding_credit_packs_tenant_id_tenants_id_fk": {
          "name": "geocoding_credit_packs_tenant_id_tenants_id_fk",
          "tableFrom": "geocoding_credit_packs",
          "tableTo": "tenants",
          "columnsFrom": [
            "tenant_id"
          ],
          "columnsTo": [
            "id"
          ],
          "onDelete": "no action",
          "onUpdate": "no action"
        }
      },
      "compositePrimaryKeys": {},
      "uniqueConstraints": {
        "geocoding_credit_packs_stripe_session_id_unique": {
          "name": "geocoding_credit_packs_stripe_session_id_unique",
          "nullsNotDistinct": false,
          "columns": [
            "stripe_session_id"
          ]
        }
      },
      "policies": {},
      "checkConstraints": {},
      "isRLSEnabled": false
    },
    "public.payments": {
      "name": "payments",
      "schema": "",
      "columns": {
        "id": {
          "name": "id",
          "type": "uuid",
          "primaryKey": true,
          "notNull": true,
          "default": "gen_random_uuid()"
        },
        "tenant_id": {
          "name": "tenant_id",
          "type": "uuid",
          "primaryKey": false,
          "notNull": true
        },
        "provider": {
          "name": "provider",
          "type": "varchar(20)",
          "primaryKey": false,
          "notNull": true,
          "default": "'stripe'"
        },
        "event_id": {
          "name": "event_id",
          "type": "varchar(200)",
          "primaryKey": false,
          "notNull": false
        },
        "type": {
          "name": "type",
          "type": "varchar(20)",
          "primaryKey": false,
          "notNull": true
        },
        "description": {
          "name": "description",
          "type": "varchar(300)",
          "primaryKey": false,
          "notNull": false
        },
        "amount_cents": {
          "name": "amount_cents",
          "type": "integer",
          "primaryKey": false,
          "notNull": true
        },
        "currency": {
          "name": "currency",
          "type": "varchar(10)",
          "primaryKey": false,
          "notNull": true,
          "default": "'brl'"
        },
        "status": {
          "name": "status",
          "type": "varchar(20)",
          "primaryKey": false,
          "notNull": true
        },
        "created_at": {
          "name": "created_at",
          "type": "timestamp",
          "primaryKey": false,
          "notNull": true,
          "default": "now()"
        }
      },
      "indexes": {},
      "foreignKeys": {
        "payments_tenant_id_tenants_id_fk": {
          "name": "payments_tenant_id_tenants_id_fk",
          "tableFrom": "payments",
          "tableTo": "tenants",
          "columnsFrom": [
            "tenant_id"
          ],
          "columnsTo": [
            "id"
          ],
          "onDelete": "no action",
          "onUpdate": "no action"
        }
      },
      "compositePrimaryKeys": {},
      "uniqueConstraints": {
        "payments_event_id_unique": {
          "name": "payments_event_id_unique",
          "nullsNotDistinct": false,
          "columns": [
            "event_id"
          ]
        }
      },
      "policies": {},
      "checkConstraints": {},
      "isRLSEnabled": false
    }
  },
  "enums": {},
  "schemas": {},
  "sequences": {},
  "roles": {},
  "policies": {},
  "views": {},
  "_meta": {
    "columns": {},
    "schemas": {},
    "tables": {}
  }
}